Metadata-Version: 2.2
Name: python-okx-ext
Version: 0.1.0
Summary: Python SDK Extension for the OKX API v5
Author-email: parker1019 <parker178912@gmail.com>
License: MIT
Project-URL: Homepage, https://okx.com/docs-v5/
Project-URL: Repository, https://github.com/parker1019/python-okx-ext
Project-URL: Documentation, https://okx.com/docs-v5/
Project-URL: Changelog, https://github.com/parker1019/python-okx-ext/releases
Keywords: OKX,crypto,trading,API,SDK
Classifier: Programming Language :: Python :: 3.9
Classifier: Programming Language :: Python :: 3.10
Classifier: Programming Language :: Python :: 3.11
Classifier: Programming Language :: Python :: 3.12
Classifier: Programming Language :: Python :: 3.13
Classifier: License :: OSI Approved :: MIT License
Classifier: Operating System :: OS Independent
Requires-Python: <4.0,>=3.9
License-File: LICENSE
Requires-Dist: httpx[http2]
Requires-Dist: keyring
Requires-Dist: loguru
Requires-Dist: requests
Requires-Dist: Twisted
Requires-Dist: pyOpenSSL
Provides-Extra: dev
Requires-Dist: pytest; extra == "dev"
Requires-Dist: black; extra == "dev"
